{"7Sc2AmuBr7e18Fbe86Wkdg==":"alg_trainees-1-676x412.jpg","Ot7nDg6F9sqnDEBorR6pkQ==":"alg_trainees-2-676x408.jpg","FE1R/GADx61CUiU9Z8Vzog==":"img_20180312-215351-676x1202.jpg","3GmygaEUiFfuuISNAbJpNw==":"img_20180312-213845-1046x588.jpg","2r+m+64ya5wkO3jYl4HQNA==":"03.jpg","G7ppxFmBiA01WEKusq5Vzg==":"01.jpg","hG16Gf981TinHFkXqWUnrQ==":"mbr-720x1080.jpg","CizagYcNCY0HSO7PFBB1KA==":"mbr-1264x1080.jpg","EHLXJz30A6msu4l2DcV76A==":"background2.jpg","expWTN1O4Gq/iblV5OhSXw==":"img_20180312-215351-1046x1860.jpg","rF5DejMFhx2wqvm7U+SqCw==":"t.10_contact-1046x2750.jpg","X/mJPoykIAgHo/eHRcFdkA==":"ezgif.com-optimize%20(1).gif","jNDgbM9VibCgqx2xGwO2LA==":"alg-trainees-1-1680x1024.jpg","5JbZz3CNAHTLBkoib2BMyw==":"img_20180312-215352-1046x1860.jpg","iDbdilPZQqjAzQKAVBG6lw==":"people_mobile.gif","tzzVbdipZv+YhvIzVdhweg==":"trainees_desktop-2.gif","LiUIORYxGXGMpCM1i0NnEA==":"06-1.jpg","vpksgFcmzMx6VyEoZ5f1Hw==":"screens_mobiles-1046x565.png","G6h5WNk6ww+u+TKsWnrkzw==":"services_hero_desktop-1046x792.jpg","ZnWdlslb7IhY3X0McfMQDw==":"services_hero_desktop-1-1046x792.jpg","Os1hpkyKHdJTZJYYSjSiXg==":"01-2.jpg","Q8kyWdiPLYJ/4F1Ss+9IyA==":"03-2.jpg","0OOE1Usrtktm437Z/qTMRQ==":"background2-1.jpg","msOEfRWmykK0CIo01U5TSg==":"surf-accounts-isometric-zoomed-1400x787-76-1046x588.jpg","aqZ2+A07mseCM7yupSlfgQ==":"surf-accounts-isometric-preview-1920x463-61-1920x463.jpg","v7r47Mqi7aHozR9XOtZr4w==":"pricing-2-1920x4510-2-1920x4510-71-800x1879.png","X/kF3AxGp02Ng3dSbQpR3w==":"surf-accounts-isometric-1920x1080-25-1920x1080.jpg","7II17ueBQEu2rmfjstIeFQ==":"surf-analysis-small-1080x608-81-1046x589.png","S7RcTCkd/o5dE091EvdNJg==":"surf-wireframe-small-1080x608-33-1046x589.png","Q/FB/iui4IGB8u4FwNM+6g==":"surfaccounts-features-2018-03-19-19_07-46-676x2786.png","J5hMD/SSlycE3cBhZOY9RA==":"alg_trainees-1-1680x1024.jpg","pP7E87VUQb8adPXVjwx5jA==":"screen%20shot%202018-03-21%20at%2012.41.30-1046x577.png","r1YTk5bc8rCNrROrVlvBcg==":"ergo_contact.gif","yhr3qTM2pqNQPGkxqtPnPA==":"screens-mobiles-1-1046x565.png","tBwG3kmubMRxaUdhoJhKkg==":"screen%20shot%202018-03-21%20at%2012.46.30-1046x577.png","XgDNVTdH0uMzMtddr2gQbg==":"screen%20shot%202018-03-21%20at%2012.42.18-676x373.png","d3Mhc+6Qb8aSzGfcB7nNHw==":"screen%20shot%202018-03-21%20at%2021.10.11-1682x1016.png","eIn1abG/u7yQDfahvQMQtA==":"screen%20shot%202018-03-21%20at%2021.12.15-1046x561.png","0CUpagl6Hjhhatk3zfRszw==":"screen%20shot%202018-03-21%20at%2021.14.03-1046x562.png","OOUUPA2O7lljZ2e3/aUtpw==":"screen%20shot%202018-03-21%20at%2021.12.41-1920x1027.png","rsnyDFwuxnxaUweRLL1OzA==":"logo.svg","G+PQHO2P39Bcs+eA+Dy4UA==":"perspective-app-screens-mock-up-1400-1400x788-74-676x380.jpg","K0cYUQiap4SvW6yrzp6uyg==":"surf-accounts-isometric-zoomed-1400x787-91-676x380.jpg","y4ATI6zPY1Zkgz+PgjnbUg==":"3-3-1920x1080-74-676x380.jpg","fhAQevN7ZFkPa0mNDEFC/w==":"ezgif-5-7759ebd53d.gif","tP/cKjtWArgS05yGYagSew==":"alumni%20network%20ui%20design%20-%20teaser-800x600.png","NYOyRpxucvte16qD5YOOZg==":"screen%20shot%202018-05-14%20at%2010.18.15-676x383.png","xU5bsrW7Q+mZghME8KZiqQ==":"screencapture-projects-invisionapp-d-main-2018-04-13-11_22-47-1046x2730.png","JR7gZZaxgCl+6ILNZ2IPsQ==":"screencapture-swrve-partners-ecosystem-2018-05-01-21_59-36-1046x3080.png"}